CHANGES.rst
MANIFEST.in
README.rst
setup.py
pyramid_odesk/__init__.py
pyramid_odesk/models.py
pyramid_odesk/tests.py
pyramid_odesk/utils.py
pyramid_odesk/views.py
pyramid_odesk.egg-info/PKG-INFO
pyramid_odesk.egg-info/SOURCES.txt
pyramid_odesk.egg-info/dependency_links.txt
pyramid_odesk.egg-info/not-zip-safe
pyramid_odesk.egg-info/requires.txt
pyramid_odesk.egg-info/top_level.txt
pyramid_odesk/templates/forbidden.jinja2