Metadata-Version: 1.1
Name: pyramid-odesk
Version: 1.1.3
Summary: pyramid_odesk
Home-page: https://github.com/kipanshi/pyramid_odesk
Author: Cyril Panshine
Author-email: kipanshi@gmail.com
License: UNKNOWN
Keywords: web pyramid pylons authentication odesk oauth
Platform: UNKNOWN
Classifier: Programming Language :: Python
Classifier: Programming Language :: Python :: 2
Classifier: Framework :: Pyramid
Classifier: Topic :: Internet :: WWW/HTTP
